pyscanprev.py
pyscanprev-0.1.0.dist-info/DESCRIPTION.rst
pyscanprev-0.1.0.dist-info/METADATA
pyscanprev-0.1.0.dist-info/RECORD
pyscanprev-0.1.0.dist-info/WHEEL
pyscanprev-0.1.0.dist-info/metadata.json
pyscanprev-0.1.0.dist-info/top_level.txt
